MANIFEST.in
README.md
REQUIREMENTS
REQUIREMENTS.test
UNLICENSE
distribute_setup.py
nose.cfg
setup.py
src/dagny/__init__.py
src/dagny/action.py
src/dagny/conneg.py
src/dagny/renderer.py
src/dagny/renderers.py
src/dagny/resource.py
src/dagny/utils.py
src/dagny.egg-info/PKG-INFO
src/dagny.egg-info/SOURCES.txt
src/dagny.egg-info/dependency_links.txt
src/dagny.egg-info/requires.txt
src/dagny.egg-info/top_level.txt
src/dagny/urls/__init__.py
src/dagny/urls/atompub.py
src/dagny/urls/rails.py
src/dagny/urls/router.py
src/dagny/urls/styles.py