Metadata-Version: 1.0
Name: dagny
Version: 0.3.0
Summary: Rails-style Resource-Oriented Architecture for Django.
Home-page: http://github.com/zacharyvoase/dagny
Author: Zachary Voase
Author-email: z@zacharyvoase.com
License: UNKNOWN
Platform: UNKNOWN
